devtoys/__init__.py
devtoys/cli.py
devtoys/test.py
devtoys-1.0.3.dist-info/LICENSE
devtoys-1.0.3.dist-info/METADATA
devtoys-1.0.3.dist-info/WHEEL
devtoys-1.0.3.dist-info/entry_points.txt
devtoys-1.0.3.dist-info/top_level.txt
devtoys-1.0.3.dist-info/RECORD
