Metadata-Version: 2.1
Name: devtoys
Version: 1.0.3
Summary: DevToys for Linux
Home-page: https://github.com/jakbin/DevToysLinux
Author: Jak Bin
Author-email: jakbin4747@gmail.com
License: MIT License
Keywords: devtoys,linux,devloper-tools
Platform: UNKNOWN
Classifier: Programming Language :: Python :: 3.6
Classifier: Natural Language :: English
Classifier: Operating System :: OS Independent
Requires-Python: >=3
License-File: LICENSE
